sciparse/__init__.py
sciparse/conftest.py
sciparse/examples/examples.py
sciparse/source/parsers.py
sciparse/source/unit_parsing.py
sciparse/test/conftest.py
sciparse/test/shorthand.py
sciparse/test/test_lcr_parsing.py
sciparse/test/test_parsing.py
sciparse/test/test_units.py
sciparse/test/data/TEST1~1~type-locked_coupled~peak-Si.txt
sciparse/test/data/lcr_test_data.dat
sciparse-0.1.24.dist-info/LICENSE.txt
sciparse-0.1.24.dist-info/METADATA
sciparse-0.1.24.dist-info/WHEEL
sciparse-0.1.24.dist-info/top_level.txt
sciparse-0.1.24.dist-info/RECORD
