Metadata-Version: 2.1
Name: sciparse
Version: 0.1.24
Summary: Python parser for Scientific datasets
Home-page: https://github.com/edmundsj/sciparse
Author: Jordan Edmunds
Author-email: edmundsj@uci.edu
License: MIT
Platform: UNKNOWN
Classifier: Programming Language :: Python :: 3
Classifier: License :: OSI Approved :: MIT License
Classifier: Operating System :: OS Independent
Requires-Python: >=3.6
License-File: LICENSE.txt
Requires-Dist: numpy (>=1.14.5)
Requires-Dist: matplotlib (>=2.0.0)
Requires-Dist: pandas (>=0.24.0)
Requires-Dist: scipy (>=1.2.2)
Requires-Dist: pyyaml (>=5.1.1)
Requires-Dist: pint (>=0.16.0)
